wetext/__init__.py
wetext/cli.py
wetext/constants.py
wetext/token_parser.py
wetext/utils.py
wetext/wetext.py
wetext/fsts/README.md
wetext/fsts/configuration.json
wetext/fsts/full_to_half.fst
wetext/fsts/remove_interjections.fst
wetext/fsts/remove_puncts.fst
wetext/fsts/tag_oov.fst
wetext/fsts/traditional_to_simple.fst
wetext/fsts/en/tn/tagger.fst
wetext/fsts/en/tn/verbalizer.fst
wetext/fsts/zh/itn/tagger.fst
wetext/fsts/zh/itn/tagger_enable_0_to_9.fst
wetext/fsts/zh/itn/verbalizer.fst
wetext/fsts/zh/tn/tagger.fst
wetext/fsts/zh/tn/verbalizer.fst
wetext/fsts/zh/tn/verbalizer_remove_erhua.fst
wetext-0.1.0.dist-info/licenses/LICENSE
wetext-0.1.0.dist-info/METADATA
wetext-0.1.0.dist-info/WHEEL
wetext-0.1.0.dist-info/entry_points.txt
wetext-0.1.0.dist-info/top_level.txt
wetext-0.1.0.dist-info/RECORD
