Metadata-Version: 2.4
Name: wetext
Version: 0.1.0
Summary: WeTextProcessing Runtime
Author-email: Zhendong Peng <pzd17@tsinghua.org.cn>
License:                                  Apache License
Project-URL: Homepage, https://github.com/pengzhendong/wetext
Project-URL: Documentation, https://github.com/pengzhendong/wetext#readme
Project-URL: BugTracker, https://github.com/pengzhendong/wetext/issues
Classifier: Programming Language :: Python :: 3
Classifier: Operating System :: OS Independent
Requires-Python: >=3.7
License-File: LICENSE
Requires-Dist: kaldifst
Dynamic: license-file
